tree_sitter_lua/__init__.py
tree_sitter_lua/__init__.pyi
tree_sitter_lua/_binding.pyd
tree_sitter_lua/binding.c
tree_sitter_lua/py.typed
tree_sitter_lua/queries/highlights.scm
tree_sitter_lua/queries/injections.scm
tree_sitter_lua/queries/locals.scm
tree_sitter_lua/queries/tags.scm
tree_sitter_lua-0.4.1.dist-info/licenses/LICENSE.md
tree_sitter_lua-0.4.1.dist-info/METADATA
tree_sitter_lua-0.4.1.dist-info/WHEEL
tree_sitter_lua-0.4.1.dist-info/top_level.txt
tree_sitter_lua-0.4.1.dist-info/RECORD
