Metadata-Version: 2.4
Name: tree-sitter-lua
Version: 0.4.1
Summary: Lua grammar for tree-sitter
Author-email: Munif Tanjim <hello@muniftanjim.dev>
License: MIT
Project-URL: Homepage, https://github.com/tree-sitter-grammars/tree-sitter-lua
Keywords: incremental,parsing,tree-sitter,lua
Classifier: Intended Audience :: Developers
Classifier: Topic :: Software Development :: Compilers
Classifier: Topic :: Text Processing :: Linguistic
Classifier: Typing :: Typed
Requires-Python: >=3.10
License-File: LICENSE.md
Provides-Extra: core
Requires-Dist: tree-sitter~=0.24; extra == "core"
Dynamic: license-file
